[
  {
    "id": "ba",
    "hideCheckbox": true,
    "title":"",
    "category": "Alignment",
    "pickOne": [
      "**Chaotic** - Eschew a convention of the civilized world.",
      "**Neutral** - Teach someone the ways of your people.",
      "Other - Describe below"
    ],
    "details": true

  },
  {
    "id": "b1",
    "title": "Placeholder",
    "description": "This is a placeholder move.",
    "outcomes": [
      {
        "range": "",
        "text": "This move does nothing and is a placeholder for future development."
      }
    ]
  }
]
